luxor/__init__.py
luxor/client.py
tests/__init__.py
tests/test_client.py
tests/test_errors.py
luxor-0.0.1.dist-info/LICENSE
luxor-0.0.1.dist-info/METADATA
luxor-0.0.1.dist-info/WHEEL
luxor-0.0.1.dist-info/top_level.txt
luxor-0.0.1.dist-info/RECORD
