Metadata-Version: 2.1
Name: luxor
Version: 0.0.1
Summary: Python module to control FX Luminaire Luxor low voltage controllers
Home-page: https://github.com/pbozeman/luxor
Author: Patrick Bozeman
Author-email: pbozeman@gmail.com
License: Apache License 2.0
Platform: UNKNOWN
Classifier: Programming Language :: Python :: 3
Classifier: Operating System :: OS Independent
License-File: LICENSE
